eclinical/__init__.py
eclinical/eclinical_cmd.py
eclinical/environment.yaml
eclinical/execption.py
eclinical/environment/__init__.py
eclinical/environment/environment.py
eclinical/environment/function_environment.py
eclinical/environment/smoke_environment.py
eclinical/record/__init__.py
eclinical/record/player.py
eclinical/record/api_spec/__init__.py
eclinical/record/api_spec/api_spec.py
eclinical/record/api_spec/swagger.py
eclinical/record/ext/__init__.py
eclinical/record/ext/common.py
eclinical/record/ext/eclinical_service.py
eclinical/record/ext/memcached.py
eclinical/record/ext/proxy.py
eclinical/record/ext/api/__init__.py
eclinical/record/ext/api/api_spec.py
eclinical/record/ext/api/swagger.py
eclinical/record/mitm/__init__.py
eclinical/record/mitm/mitm_addons.py
eclinical/record/mitm/mitm_process.py
eclinical/record/view/__init__.py
eclinical/record/view/alert_dialog.py
eclinical/record/view/record_ui.py
eclinical/record/view/status.py
eclinical/scaffold/__init__.py
eclinical/scaffold/command/__init__.py
eclinical/scaffold/command/ecl.py
eclinical/scaffold/command/edk.py
eclinical/scaffold/command/mc.py
eclinical/scaffold/command/sc.py
eclinical/scaffold/command/resource/__init__.py
eclinical/scaffold/command/resource/global_conftest.txt
eclinical/scaffold/command/resource/init_environment.yaml
eclinical/scaffold/files/__init__.py
eclinical/scaffold/files/gen_meta.py
eclinical/scaffold/files/gen_service.py
eclinical/scaffold/inputs/__init__.py
eclinical/scaffold/inputs/application.py
eclinical/scaffold/inputs/component/__init__.py
eclinical/scaffold/inputs/component/radio.py
eclinical/scaffold/inputs/component/text.py
eclinical/scaffold/inputs/ecl/__init__.py
eclinical/scaffold/inputs/ecl/module_name.py
eclinical/scaffold/inputs/ecl/module_service.py
eclinical/scaffold/inputs/ecl/module_type.py
eclinical/scaffold/inputs/edk/__init__.py
eclinical/scaffold/inputs/edk/account.py
eclinical/scaffold/inputs/edk/company.py
eclinical/scaffold/inputs/edk/db_host.py
eClinical-1.0.13.dist-info/LICENSE
eClinical-1.0.13.dist-info/METADATA
eClinical-1.0.13.dist-info/WHEEL
eClinical-1.0.13.dist-info/entry_points.txt
eClinical-1.0.13.dist-info/top_level.txt
eClinical-1.0.13.dist-info/RECORD
