Metadata-Version: 2.1
Name: eClinical
Version: 1.0.13
Summary: Tools for work
Home-page: https://github.com/xxxx
Author: thcpc
Author-email: pengcheng.chen@edetek.com
Project-URL: Bug Tracker, https://github.com/xxxx
Classifier: Programming Language :: Python :: 3
Classifier: License :: OSI Approved :: MIT License
Classifier: Operating System :: OS Independent
Requires-Python: >=3.9
License-File: LICENSE
Requires-Dist: cjen
Requires-Dist: pycryptodome
